ophac_cpp.cpython-37m-darwin.so
ophac_cpp-0.3.0.dist-info/METADATA
ophac_cpp-0.3.0.dist-info/WHEEL
ophac_cpp-0.3.0.dist-info/top_level.txt
ophac_cpp-0.3.0.dist-info/RECORD
