Metadata-Version: 2.1
Name: ophac-cpp
Version: 0.3.0
Summary: C++ implementation of parts of ophac to improve performance.
Home-page: https://bitbucket.org/Bakkelund/ophac
Author: Daniel Bakkelund
Author-email: daniel_bakkelund@hotmail.com
License: UNKNOWN
Platform: UNKNOWN
